iman/AUG.py
iman/Audio.py
iman/Boors.py
iman/Enhance.py
iman/Image.py
iman/Rar.py
iman/Report.py
iman/Text.py
iman/__init__.py
iman/examples.py
iman/gpu_info.py
iman/info.py
iman/matlab.py
iman/metrics.py
iman/par.py
iman/tf.py
iman/torch.py
iman/tsne.py
iman/vad.py
iman/web.py
iman/xvector.py
iman/yt.py
iman/Features/__init__.py
iman/Features/mfcc/LS.py
iman/Features/mfcc/SB.py
iman/Features/mfcc/__init__.py
iman/Features/mfcc/getmfcc_from_librosa.py
iman/Features/mfcc/sb_mfcc_class.py
iman/examples_folder/__init__.py
iman/examples_folder/age.py
iman/examples_folder/ffmpeg.py
iman/examples_folder/flask.py
iman/examples_folder/gpu_allocate_tf.py
iman/examples_folder/graphviz_chart.py
iman/examples_folder/parallel.py
iman/examples_folder/post_by_python.py
iman/examples_folder/pyworldd.py
iman/examples_folder/queue_worker.py
iman/examples_folder/save_docx.py
iman/examples_folder/stft_test.py
iman/examples_folder/threading_example.py
iman/examples_folder/wikipedia.py
iman/lib_v5/__init__.py
iman/lib_v5/pyrb.py
iman/lib_v5/spec_utils.py
iman/lib_v5/vr_network/__init__.py
iman/lib_v5/vr_network/layers_new.py
iman/lib_v5/vr_network/model_param_init.py
iman/lib_v5/vr_network/nets_new.py
iman/num2fa/__init__.py
iman/num2fa/__main__.py
iman/pyctcdecode/__init__.py
iman/pyctcdecode/alphabet.py
iman/pyctcdecode/constants.py
iman/pyctcdecode/decoder.py
iman/pyctcdecode/language_model.py
iman/sad_tf/__init__.py
iman/sad_tf/export_funcs.py
iman/sad_tf/features.py
iman/sad_tf/segmenter.py
iman/sad_tf/segmenter_for_tf2_16.py
iman/sad_tf/segmentero.py
iman/sad_tf/sidekit_mfcc.py
iman/sad_tf/thread_returning.py
iman/sad_tf/viterbi.py
iman/sad_tf/viterbi_utils.py
iman/sad_tf_mlp/__init__.py
iman/sad_tf_mlp/export_funcs.py
iman/sad_tf_mlp/features.py
iman/sad_tf_mlp/segmenter.py
iman/sad_tf_mlp/sidekit_mfcc.py
iman/sad_tf_mlp/thread_returning.py
iman/sad_tf_mlp/viterbi.py
iman/sad_tf_mlp/viterbi_utils.py
iman/sad_tf_mlp_speaker/__init__.py
iman/sad_tf_mlp_speaker/features.py
iman-2.0.3.dist-info/METADATA
iman-2.0.3.dist-info/WHEEL
iman-2.0.3.dist-info/top_level.txt
iman-2.0.3.dist-info/RECORD
