Metadata-Version: 2.1
Name: iman
Version: 2.0.3
Summary: Python package for daily Tasks
Author: Iman Sarraf
Author-email: imansarraf@gmail.com
Keywords: python,iman
Classifier: Development Status :: 3 - Alpha
Classifier: Intended Audience :: Education
Classifier: Programming Language :: Python :: 3
Requires-Dist: scipy
Requires-Dist: numpy
Requires-Dist: six
Requires-Dist: matplotlib
Requires-Dist: joblib
